cloupy/__init__.py
cloupy/data_processing/check_data_continuity.py
cloupy/diagrams/walter_lieth.py
cloupy/maps/draw_shapes.py
cloupy/maps/interpolation_map.py
cloupy/maps/world/ne_50m_admin_0_countries.cpg
cloupy/maps/world/ne_50m_admin_0_countries.dbf
cloupy/maps/world/ne_50m_admin_0_countries.prj
cloupy/maps/world/ne_50m_admin_0_countries.shp
cloupy/maps/world/ne_50m_admin_0_countries.shx
cloupy/scraping/imgw.py
cloupy/scraping/imgw_coordinates.csv
cloupy/scraping/wmo.py
cloupy/scraping/wmo_ids_and_coords.csv
cloupy/test/test_integration/test_integration_imgw.py
cloupy/test/test_integration/test_integration_interpolation_map.py
cloupy/test/test_integration/test_integration_walter_lieth.py
cloupy/test/test_integration/test_integration_wmo.py
cloupy/test/test_unit/test_unittest_check_data_continuity.py
cloupy/test/test_unit/test_unittest_drawing_shapes.py
cloupy/test/test_unit/test_unittest_imgw.py
cloupy/test/test_unit/test_unittest_interpolation_map.py
cloupy/test/test_unit/test_unittest_walter_lieth.py
cloupy/test/test_unit/test_unittest_wmo.py
cloupy-2.0.0.dist-info/LICENSE.md
cloupy-2.0.0.dist-info/METADATA
cloupy-2.0.0.dist-info/WHEEL
cloupy-2.0.0.dist-info/top_level.txt
cloupy-2.0.0.dist-info/RECORD
