Metadata-Version: 2.1
Name: cloupy
Version: 2.0.0
Summary: The package allows to download, process and visualize climatological data from reliable sources
Home-page: https://github.com/pdGruby/cloupy
Author: Kamil Grala
Author-email: kamil.grala32466@gmail.com
License: MIT
Classifier: Development Status :: 5 - Production/Stable
Classifier: Programming Language :: Python :: 3
Classifier: Programming Language :: Python :: 3.8
Classifier: Programming Language :: Python :: 3.9
Classifier: Programming Language :: Python :: 3.10
Classifier: Operating System :: Microsoft :: Windows :: Windows 10
Classifier: Operating System :: POSIX :: Linux
Classifier: Intended Audience :: Education
Classifier: Intended Audience :: Science/Research
Classifier: Framework :: Matplotlib
Classifier: Topic :: Scientific/Engineering :: GIS
Classifier: Topic :: Scientific/Engineering :: Atmospheric Science
Classifier: Topic :: Scientific/Engineering :: Visualization
License-File: LICENSE.md
Requires-Dist: pandas (<=1.3.5,>=1.3.3)
Requires-Dist: matplotlib (<=3.5.1,>=3.4.3)
Requires-Dist: requests (<=2.27.1,>=2.26.0)
Requires-Dist: beautifulsoup4 (<=4.10.0,>=4.9.3)
Requires-Dist: numpy (<=1.22.1,>=1.21.4)
Requires-Dist: pyshp (==2.1.3)
Requires-Dist: pyproj (<=3.3.0,>=3.2.1)
Requires-Dist: scipy (<=1.7.3,>=1.7.2)
Requires-Dist: Pillow (<=9.0.0,>=8.4.0)
Requires-Dist: cycler (==0.11.0)
